{
	"flight_boundaries": [{"longitude":38.1462694444, "latitude":-76.4281638889},
			      {"longitude":38.151625, 	  "latitude":-76.4286833333},
			      {"longitude":38.1518888889, "latitude":-76.4314666667},
			      {"longitude":38.1505944444, "latitude":-76.4353611111},
			      {"longitude":38.1475666667, "latitude":-76.4323416667},
			      {"longitude":38.1446666667, "latitude":-76.4329472222},
			      {"longitude":38.1432555556, "latitude":-76.4347666667},
			      {"longitude":38.1404638889, "latitude":-76.4326361111},
			      {"longitude":38.1407194444, "latitude":-76.4260138889},
			      {"longitude":38.1437611111, "latitude":-76.4212055556},
			      {"longitude":38.1473472222, "latitude":-76.4232111111},
			      {"longitude":38.1461305556, "latitude":-76.4266527778}],
	"SRIC_Position": {
				"longitude":-76.4266013,
				"latitude":38.1470837
			 }
}

